smrnatk/__about__.py
smrnatk/__init__.py
smrnatk/align.py
smrnatk/collapse.py
smrnatk/collate.py
smrnatk/common.py
smrnatk/filter_fasta.py
smrnatk/quality_parse.py
smrnatk-0.1.0.dist-info/METADATA
smrnatk-0.1.0.dist-info/WHEEL
smrnatk-0.1.0.dist-info/entry_points.txt
smrnatk-0.1.0.dist-info/RECORD
