Metadata-Version: 2.1
Name: smrnatk
Version: 0.1.0
Summary: The small RNA toolkit (smRNAtk) is a comprehensive set of utilities built for the purpose of cleaning and analyzing raw RNA NGS data
License: MIT
Keywords: bioinformatics
Author: Adam Labadorf
Author-email: labadorf@bu.edu
Requires-Python: >=3.10,<4.0
Classifier: Environment :: Console
Classifier: Intended Audience :: Science/Research
Classifier: License :: OSI Approved :: MIT License
Classifier: Operating System :: OS Independent
Classifier: Programming Language :: Python :: 3
Classifier: Programming Language :: Python :: 3.10
Classifier: Programming Language :: Python :: 3.11
Classifier: Programming Language :: Python :: 3.12
Classifier: Programming Language :: Python :: 3.13
Classifier: Topic :: Scientific/Engineering :: Bio-Informatics
Requires-Dist: de-toolkit (>=0.9.12,<0.10.0)
Requires-Dist: pysam (>=0.22.1,<0.23.0)
Requires-Dist: requests (>=2.28.0,<3.0.0)
